edgecom/__init__.py
edgecom/base_request.py
edgecom/edge_sdk.py
edgecom/modbus.py
mysdk/__init__.py
mysdk/edge_sdk.py
sineva_edge_sdk-1.5.dist-info/METADATA
sineva_edge_sdk-1.5.dist-info/WHEEL
sineva_edge_sdk-1.5.dist-info/top_level.txt
sineva_edge_sdk-1.5.dist-info/RECORD
