Metadata-Version: 2.1
Name: sineva-edge-sdk
Version: 1.5
Summary: A  module for test
Home-page: https://github.com/vfrtgb158/email
Author: tower
Author-email: chengtao@sineva.com.cn
License: MIT
Platform: UNKNOWN
Requires: requests
Requires: urllib3
